baseline/__init__.py
baseline/main.py
baseline_cli-0.1.0.dist-info/METADATA
baseline_cli-0.1.0.dist-info/WHEEL
baseline_cli-0.1.0.dist-info/entry_points.txt
baseline_cli-0.1.0.dist-info/top_level.txt
baseline_cli-0.1.0.dist-info/RECORD
